atpthings/__init__.py
atpthings/_version.py
atpthings/client_redis/__init__.py
atpthings/database/__init__.py
atpthings/database/data_entity.py
atpthings/database/data_timeseries.py
atpthings/dict/__init__.py
atpthings/dict/convert.py
atpthings/dict/get.py
atpthings/dict/io.py
atpthings/util/__init__.py
atpthings-0.0.44.dist-info/LICENSE
atpthings-0.0.44.dist-info/METADATA
atpthings-0.0.44.dist-info/WHEEL
atpthings-0.0.44.dist-info/entry_points.txt
atpthings-0.0.44.dist-info/top_level.txt
atpthings-0.0.44.dist-info/RECORD
