Metadata-Version: 2.1
Name: atpthings
Version: 0.0.44
Summary: ATP-things python package
Author-email: Andraz Polak <andrazpolak@gmail.com>
License: MIT
Project-URL: homepage, https://github.com/atp-things/pkg-python-util
Project-URL: documentation, https://atp-things.github.io/pkg-python-util/
Project-URL: repository, https://github.com/atp-things/pkg-python-util
Keywords: atpthings,iot
Classifier: Programming Language :: Python
Classifier: Programming Language :: Python :: 3
Classifier: Operating System :: OS Independent
Requires-Python: >=3.8
License-File: LICENSE
Requires-Dist: pymongo
Requires-Dist: pandas
Requires-Dist: pyyaml
